{"place":"Hagerty High School","name":"FL FTC Seminole County League Championship","date":"27-Jan-13","handle":"oBtPTL","teams":[{"highest":22,"QP":4,"RP":33,"matches":7,"name":"Robot Unicorn","number":128},{"highest":100,"QP":8,"RP":85,"matches":7,"name":"Electric Narwhals","number":132},{"highest":81,"QP":3,"RP":103,"matches":7,"name":"Quite Fancy","number":531},{"highest":100,"QP":3,"RP":75,"matches":7,"name":"Maximum Chaos","number":532},{"highest":125,"QP":8,"RP":252,"matches":7,"name":"Built and Dangerous (B.A.D)","number":3045},{"highest":125,"QP":11,"RP":81,"matches":7,"name":"Kiss My Bot!","number":4227},{"highest":115,"QP":9,"RP":146,"matches":6,"name":"Gears of Other Dimensions (G.O.O.D)","number":4228},{"highest":60,"QP":6,"RP":59,"matches":7,"name":"Cronus","number":4304},{"highest":85,"QP":10,"RP":96,"matches":7,"name":" Estrogenius","number":4717}]}