{"place":"Polytechnic University","name":"FL FTC Orange County League Meet #2","date":"15-Dec-12","handle":"YO4eFZ","teams":[{"highest":187,"QP":7,"RP":141,"matches":6,"name":"Maelstrom","number":3846},{"highest":50,"QP":4,"RP":32,"matches":6,"name":"Robo GT","number":3939},{"highest":91,"QP":8,"RP":91,"matches":6,"name":"Team Brick Buddies","number":5018},{"highest":103,"QP":8,"RP":180,"matches":6,"name":"N.U.T.S.","number":5070},{"highest":45,"QP":2,"RP":28,"matches":6,"name":"Motor Monkeys","number":5286},{"highest":91,"QP":11,"RP":80,"matches":6,"name":"ditu","number":5454},{"highest":102,"QP":7,"RP":2,"matches":6,"name":"Renaissance Robotics","number":5937},{"highest":61,"QP":5,"RP":16,"matches":6,"name":"G360","number":6090},{"highest":103,"QP":2,"RP":184,"matches":6,"name":"Robotica","number":6130},{"highest":23,"QP":4,"RP":11,"matches":6,"name":"Purple Nurple","number":6323},{"highest":187,"QP":10,"RP":114,"matches":6,"name":"FETCH","number":6327},{"highest":110,"QP":4,"RP":33,"matches":6,"name":"Nerdvana","number":6379}]}